SDK/__init__.py
SDK/anthropic.py
SDK/core.py
SDK/gemini.py
SDK/openai.py
llm_unified_sdk-0.1.0.dist-info/METADATA
llm_unified_sdk-0.1.0.dist-info/WHEEL
llm_unified_sdk-0.1.0.dist-info/top_level.txt
llm_unified_sdk-0.1.0.dist-info/RECORD
