Metadata-Version: 2.4
Name: llm-unified-sdk
Version: 0.1.0
Summary: Python SDK for the Unified LLM Chat Backend API.
Author: NTV
Classifier: Programming Language :: Python :: 3
Classifier: Operating System :: OS Independent
Requires-Python: >=3.8
Requires-Dist: requests>=2.20
